mykonos/__init__.py
mykonos/setting.py
mykonos/core/__init__.py
mykonos/core/core.py
mykonos/core/helpers.py
mykonos/keywords/__init__.py
mykonos/keywords/decorators.py
mykonos/keywords/element.py
mykonos/keywords/key_event.py
mykonos/keywords/keywordgroup.py
mykonos/keywords/management_device.py
mykonos/keywords/management_device_utils.py
mykonos/keywords/prerequest.py
mykonos/keywords/touch.py
mykonos/keywords/wait.py
mykonos/locator/__init__.py
mykonos/locator/locator_element.py
mykonos-1.5.4.dist-info/LICENSE
mykonos-1.5.4.dist-info/METADATA
mykonos-1.5.4.dist-info/WHEEL
mykonos-1.5.4.dist-info/top_level.txt
mykonos-1.5.4.dist-info/RECORD
