Metadata-Version: 2.1
Name: mykonos
Version: 1.5.4
Summary: Robot Framework Mobile Test Automation using UIAutomator
Home-page: https://github.com/monicadanesa/mykonos
Author: Monica Danesa and Ahmad Kadafi
Author-email: monicadanesa@gmail.com, andriana.khadafi@gmail.com
License: UNKNOWN
Keywords: Robot Framework Mobile Test Automation using UIAutomator
Platform: UNKNOWN
Requires-Dist: uiautomator (>=0.1.28)
Requires-Dist: alog
Requires-Dist: robotframework (>=2.6.0)
